snake_wars/__init__.py
snake_wars/client/__init__.py
snake_wars/client/client.py
snake_wars/client/renderer.py
snake_wars/client/entities/__init__.py
snake_wars/client/entities/food.py
snake_wars/client/entities/snake.py
snake_wars/commons/__init__.py
snake_wars/commons/direction.py
snake_wars/commons/location.py
snake_wars/commons/random_location.py
snake_wars/commons/size.py
snake_wars/server/__init__.py
snake_wars/server/player.py
snake_wars/server/server.py
snake_wars/server/entities/__init__.py
snake_wars/server/entities/food.py
snake_wars/server/entities/snake.py
snake_wars/server/web/__init__.py
snake_wars-0.1.0.dist-info/LICENSE.md
snake_wars-0.1.0.dist-info/METADATA
snake_wars-0.1.0.dist-info/WHEEL
snake_wars-0.1.0.dist-info/top_level.txt
snake_wars-0.1.0.dist-info/RECORD
